[
{
           "league": "AFF U19 Championship",
            "date": "July 6",
            "time": "(2:30) PM",
            "himg": "https://images.fotmob.com/image_resources/logo/teamlogo/8307.png",
            "aimg": "https://images.fotmob.com/image_resources/logo/teamlogo/230139.png",
            "teams" : "Myanmar Vs Philipines",
            "hteam" : "Myanmar",
            "ateam" : "Philipines",
            "link":[
                {
                    "type": "HD",
                "livelink":"0"
                }
            ]
         },
{
           "league": "AFF U19 Championship",
            "date": "July 6",
            "time": "(4:30) PM",
            "himg": "https://images.fotmob.com/image_resources/logo/teamlogo/178671.png",
            "aimg": "https://images.fotmob.com/image_resources/logo/teamlogo/5894.png",
            "teams" : "Brunei Vs Vietnam",
            "hteam" : "Brunei",
            "ateam" : "Vietnam",
            "link":[
                {
                    "type": "HD",
                "livelink":"0"
                }
            ]
         },
{
           "league": "AFF U19 Championship",
            "date": "July 6",
            "time": "(7:30) PM",
            "himg": "https://images.fotmob.com/image_resources/logo/teamlogo/840190.png",
            "aimg": "https://images.fotmob.com/image_resources/logo/teamlogo/5788.png",
            "teams" : "Indonesia Vs Thailand",
            "hteam" : "Indonesia",
            "ateam" : "Thailand",
            "link":[
                {
                    "type": "HD",
                "livelink":"0"
                }
            ]
         },
{
           "league": "Champions League Qlf",
            "date": "July 6",
            "time": "(8:30) PM",
            "himg": "https://images.fotmob.com/image_resources/logo/teamlogo/7983_small.png",
            "aimg": "https://images.fotmob.com/image_resources/logo/teamlogo/8222_small.png",
            "teams" : "Tobol Kostanay Vs Ferencvaros",
            "hteam" : "Tobol Kostanav",
            "ateam" : "Ferencvaros",
            "link":[
                {
                    "type": "HD",
                "livelink":"0"
                }
              
            ]
         },
{
           "league": "Club Friendly",
            "date": "July 12",
            "time": "(7:30) PM",
            "himg": "https://images.fotmob.com/image_resources/logo/teamlogo/8650.png",
            "aimg": "https://images.fotmob.com/image_resources/logo/teamlogo/10260.png",
            "teams" : "Liverpool Vs Man U",
            "hteam" : "Liverpool",
            "ateam" : "Man U",
            "link":[
                {
                    "type": "HD",
                "livelink":"0"
                }
            ]
         }
]
